nonebot_plugin_mcplayer_render/__init__.py
nonebot_plugin_mcplayer_render-1.0.3.dist-info/LICENSE
nonebot_plugin_mcplayer_render-1.0.3.dist-info/METADATA
nonebot_plugin_mcplayer_render-1.0.3.dist-info/WHEEL
nonebot_plugin_mcplayer_render-1.0.3.dist-info/RECORD
