Metadata-Version: 2.3
Name: nonebot-plugin-mcplayer-render
Version: 1.0.3
Summary: 正版玩家信息查询与皮肤渲染
License: MIT
Keywords: mc,nonebot
Author: Polaris_Light
Author-email: 995905922@qq.com
Requires-Python: >=3.10
Classifier: License :: OSI Approved :: MIT License
Classifier: Programming Language :: Python :: 3
Classifier: Programming Language :: Python :: 3.10
Classifier: Programming Language :: Python :: 3.11
Classifier: Programming Language :: Python :: 3.12
Classifier: Programming Language :: Python :: 3.13
Requires-Dist: aiohttp (>=3.8.0)
Requires-Dist: nonebot-adapter-onebot (>=2.0.0)
Requires-Dist: nonebot2 (>=2.2.1)
Project-URL: Homepage, https://github.com/GLDYM/nonebot-plugin-mcplayer-render
